sungrow_http_config/SungrowHttpConfig.py
sungrow_http_config/__init__.py
sungrow_http_config-0.2.0.dist-info/METADATA
sungrow_http_config-0.2.0.dist-info/WHEEL
sungrow_http_config-0.2.0.dist-info/top_level.txt
sungrow_http_config-0.2.0.dist-info/RECORD
