Metadata-Version: 2.4
Name: sungrow_http_config
Version: 0.2.0
Summary: A package to manipulate settings on Sungrow Inverters
Author-email: Ross Williamson <ross@inertia.net.nz>
License-Expression: MIT
Project-URL: Homepage, https://github.com/ross-w/sungrow_http_config
Project-URL: Bug Tracker, https://github.com/ross-w/sungrow_http_config/issues
Classifier: Programming Language :: Python :: 3
Classifier: Operating System :: OS Independent
Requires-Python: >=3.9
Requires-Dist: tenacity
Requires-Dist: urllib3
Requires-Dist: pymodbus<4.0,>=3.0
Requires-Dist: requests
Requires-Dist: SungrowModbusTcpClient-jesseklm>=0.1.9
Provides-Extra: dev
Requires-Dist: ruff<1.0.0,>=0.12.0; extra == "dev"
